verda/__init__.py
verda/_verda.py
verda/_version.py
verda/authentication/__init__.py
verda/authentication/_authentication.py
verda/balance/__init__.py
verda/balance/_balance.py
verda/clusters/__init__.py
verda/clusters/_clusters.py
verda/constants.py
verda/containers/__init__.py
verda/containers/_containers.py
verda/exceptions.py
verda/helpers.py
verda/http_client/__init__.py
verda/http_client/_http_client.py
verda/images/__init__.py
verda/images/_images.py
verda/inference_client/__init__.py
verda/inference_client/_inference_client.py
verda/instance_types/__init__.py
verda/instance_types/_instance_types.py
verda/instances/__init__.py
verda/instances/_instances.py
verda/locations/__init__.py
verda/locations/_locations.py
verda/ssh_keys/__init__.py
verda/ssh_keys/_ssh_keys.py
verda/startup_scripts/__init__.py
verda/startup_scripts/_startup_scripts.py
verda/volume_types/__init__.py
verda/volume_types/_volume_types.py
verda/volumes/__init__.py
verda/volumes/_volumes.py
verda-1.19.0.dist-info/WHEEL
verda-1.19.0.dist-info/METADATA
verda-1.19.0.dist-info/RECORD
