Metadata-Version: 2.3
Name: verda
Version: 1.19.0
Summary: Official Python SDK for Verda (formerly DataCrunch) Public API
Author: Verda Cloud Oy
Author-email: Verda Cloud Oy <info@verda.com>
Classifier: Development Status :: 5 - Production/Stable
Classifier: Intended Audience :: Developers
Classifier: License :: OSI Approved :: MIT License
Classifier: Natural Language :: English
Classifier: Operating System :: OS Independent
Classifier: Programming Language :: Python :: 3
Classifier: Programming Language :: Python :: 3.10
Classifier: Programming Language :: Python :: 3.11
Classifier: Programming Language :: Python :: 3.12
Classifier: Programming Language :: Python :: 3.13
Classifier: Programming Language :: Python :: 3.14
Requires-Dist: requests>=2.25.1,<3
Requires-Dist: dataclasses-json>=0.6.7
Requires-Python: >=3.10
Project-URL: Changelog, https://github.com/verda-cloud/sdk-python/blob/master/CHANGELOG.md
Project-URL: Documentation, https://datacrunch-python.readthedocs.io/
Project-URL: Homepage, https://github.com/verda-cloud
Project-URL: Repository, https://github.com/verda-cloud/sdk-python
